limburg_flood_impact/__init__.py
limburg_flood_impact/_functions.py
limburg_flood_impact/check_address.py
limburg_flood_impact/classify_area_wide_rain.py
limburg_flood_impact/classify_rural_rain.py
limburg_flood_impact/classify_urban_rain.py
limburg_flood_impact/combine_classification.py
limburg_flood_impact/extent_tile.py
limburg_flood_impact/test_against_flood_protection_norm.py
limburg_flood_impact/bin/__init__.py
limburg_flood_impact/bin/check_address.py
limburg_flood_impact/bin/classify_area_wide_rain.py
limburg_flood_impact/bin/classify_rural_rain.py
limburg_flood_impact/bin/classify_urban_rain.py
limburg_flood_impact/bin/combine_classification.py
limburg_flood_impact/bin/test_against_flood_protection_norm.py
limburg_flood_impact-0.8.0.dist-info/METADATA
limburg_flood_impact-0.8.0.dist-info/WHEEL
limburg_flood_impact-0.8.0.dist-info/entry_points.txt
limburg_flood_impact-0.8.0.dist-info/top_level.txt
limburg_flood_impact-0.8.0.dist-info/RECORD
