Metadata-Version: 2.1
Name: limburg-flood-impact
Version: 0.8.0
Summary: Libmurg Flood Impact Package.
Home-page: https://github.com/
Author: Lutra Consulting Ltd.
Author-email: jan.caha@lutraconsulting.co.uk
License: MIT
Project-URL: Documentation, https://
Platform: any
Requires-Python: >=3.6
Requires-Dist: numpy
Requires-Dist: GDAL
